airshare/__init__.py
airshare/cli.py
airshare/exception.py
airshare/qrcode.py
airshare/receiver.py
airshare/sender.py
airshare/utils.py
airshare/static/download.html
airshare/static/text.html
airshare/static/upload.html
Airshare-0.1.6.dist-info/LICENSE.md
Airshare-0.1.6.dist-info/METADATA
Airshare-0.1.6.dist-info/WHEEL
Airshare-0.1.6.dist-info/entry_points.txt
Airshare-0.1.6.dist-info/top_level.txt
Airshare-0.1.6.dist-info/RECORD
