Metadata-Version: 2.1
Name: Airshare
Version: 0.1.6
Summary: Cross-platform content sharing in a local network.
Home-page: https://github.com/KuroLabs/airshare
Author: Kandavel A, Mohanasundar M, Nanda H Krishna
Author-email: kurolabs.org+airshare@gmail.com
License: UNKNOWN
Platform: UNKNOWN
Classifier: Environment :: Console
Classifier: License :: OSI Approved :: MIT License
Classifier: Operating System :: OS Independent
Classifier: Programming Language :: Python :: 3.6
Classifier: Programming Language :: Python :: 3.7
Classifier: Programming Language :: Python :: 3.8
Classifier: Topic :: System :: Networking
Classifier: Topic :: Utilities
Requires-Python: >=3.6
Requires-Dist: aiohttp (>=3.6.2)
Requires-Dist: asyncio (>=3.4.3)
Requires-Dist: click (>=7.0)
Requires-Dist: colorama (>=0.4.3)
Requires-Dist: humanize (>=0.5.1)
Requires-Dist: pyperclip (>=1.8.0)
Requires-Dist: requests (>=2.20.0)
Requires-Dist: requests-toolbelt (>=0.9.1)
Requires-Dist: termcolor (>=1.1.0)
Requires-Dist: tqdm (>=4.36.1)
Requires-Dist: zeroconf (>=0.25.0)
